trollius_fixers/__init__.py
trollius_fixers/fix_decorator.py
trollius_fixers/fix_import_from_return.py
trollius_fixers/fix_imports.py
trollius_fixers/fix_raise_return.py
trollius_fixers/fix_yield_from.py
trollius_fixers/trollius2asyncio.py
trollius_fixers-0.2.dist-info/LICENSE.txt
trollius_fixers-0.2.dist-info/METADATA
trollius_fixers-0.2.dist-info/WHEEL
trollius_fixers-0.2.dist-info/entry_points.txt
trollius_fixers-0.2.dist-info/top_level.txt
trollius_fixers-0.2.dist-info/RECORD
