Metadata-Version: 2.1
Name: trollius-fixers
Version: 0.2
Summary: Convert trollius code to asyncio
Home-page: https://github.com/bmerry/trollius-fixers
Author: Bruce Merry
License: MIT
Keywords: 2to3 asyncio trollius
Platform: UNKNOWN
Classifier: Development Status :: 4 - Beta
Classifier: Intended Audience :: Developers
Classifier: License :: OSI Approved :: MIT License
Classifier: Operating System :: OS Independent
Classifier: Programming Language :: Python :: 2
Classifier: Programming Language :: Python :: 3
Classifier: Topic :: System :: Networking
